mwrefs/__init__.py
mwrefs/about.py
mwrefs/extract.py
mwrefs/mwrefs.py
mwrefs/references/__init__.py
mwrefs/references/extract.py
mwrefs/tests/__init__.py
mwrefs/tests/test_extract.py
mwrefs/utilities/__init__.py
mwrefs/utilities/diffs.py
mwrefs/utilities/extract.py
mwrefs/utilities/fetch_references.py
mwrefs/utilities/util.py
mwrefs-0.0.3.dist-info/DESCRIPTION.rst
mwrefs-0.0.3.dist-info/METADATA
mwrefs-0.0.3.dist-info/RECORD
mwrefs-0.0.3.dist-info/WHEEL
mwrefs-0.0.3.dist-info/entry_points.txt
mwrefs-0.0.3.dist-info/metadata.json
mwrefs-0.0.3.dist-info/top_level.txt
