Metadata-Version: 2.0
Name: mwrefs
Version: 0.0.3
Summary: A set of utilities for extracting and processing <ref>s MediaWiki Projects
Home-page: https://github.com/mediawiki-utilities/python-mwrefs
Author: Aaron Halfaker
Author-email: aaron.halfaker@gmail.com
License: MIT
Platform: UNKNOWN
Requires-Dist: mwapi
Requires-Dist: mwcli
